{
  "markets": [
    {
      "title": "Will Olympique Lyonnais win on 2026-0...",
      "price": 0.18,
      "volume": 2541104.45,
      "source": "Polymarket"
    },
    {
      "title": "US x Iran ceasefire by April 7?",
      "price": 0.033,
      "volume": 1767622.71,
      "source": "Polymarket"
    },
    {
      "title": "Will the Iranian regime fall by April...",
      "price": 0.0385,
      "volume": 1641809.43,
      "source": "Polymarket"
    },
    {
      "title": "Will 1. FC Union Berlin win on 2026-0...",
      "price": 0.355,
      "volume": 1035660.98,
      "source": "Polymarket"
    },
    {
      "title": "Will the San Antonio Spurs win the 20...",
      "price": 0.177,
      "volume": 847855.32,
      "source": "Polymarket"
    },
    {
      "title": "Will Gavin Newsom win the 2028 US Pre...",
      "price": 0.167,
      "volume": 771280.13,
      "source": "Polymarket"
    },
    {
      "title": "Will the U.S. invade Iran before 2027?",
      "price": 0.575,
      "volume": 724086.23,
      "source": "Polymarket"
    },
    {
      "title": "US x Iran ceasefire by April 30?",
      "price": 0.225,
      "volume": 720699.83,
      "source": "Polymarket"
    }
  ],
  "sources": {
    "polymarket": true,
    "kalshi": false
  }
}