{
  "markets": [
    {
      "title": "Will Roberto S\u00e1nchez Palomino win the...",
      "price": 0.144,
      "volume": 2016857.3,
      "source": "Polymarket"
    },
    {
      "title": "Will Rafael L\u00f3pez Aliaga win the 2026...",
      "price": 0.315,
      "volume": 1246894.1,
      "source": "Polymarket"
    },
    {
      "title": "Will Keiko Fujimori win the 2026 Peru...",
      "price": 0.495,
      "volume": 1218739.04,
      "source": "Polymarket"
    },
    {
      "title": "Hurricanes vs. Flyers",
      "price": 0.405,
      "volume": 1206844.67,
      "source": "Polymarket"
    },
    {
      "title": "Will Jorge Nieto win the 2026 Peruvia...",
      "price": 0.0345,
      "volume": 1154894.1,
      "source": "Polymarket"
    },
    {
      "title": "Wild vs. Blues",
      "price": 0.375,
      "volume": 1121653.31,
      "source": "Polymarket"
    }
  ],
  "sources": {
    "polymarket": true,
    "kalshi": false
  }
}