{
  "markets": [
    {
      "title": "Cavaliers vs. Raptors",
      "price": 0.755,
      "volume": 3349616.58,
      "source": "Polymarket"
    },
    {
      "title": "Spurs vs. Trail Blazers",
      "price": 0.665,
      "volume": 3250138.21,
      "source": "Polymarket"
    },
    {
      "title": "Will Olympique de Marseille win on 20...",
      "price": 0.585,
      "volume": 1667260.5,
      "source": "Polymarket"
    },
    {
      "title": "US x Iran permanent peace deal by Apr...",
      "price": 0.0235,
      "volume": 1351348.67,
      "source": "Polymarket"
    }
  ],
  "sources": {
    "polymarket": true,
    "kalshi": false
  }
}