{
  "markets": [
    {
      "title": "US forces enter Iran by March 31?",
      "price": 0.165,
      "volume": 3117046.21,
      "source": "Polymarket"
    },
    {
      "title": "US x Iran ceasefire by March 31?",
      "price": 0.0315,
      "volume": 2730505.59,
      "source": "Polymarket"
    },
    {
      "title": "New York Yankees vs. San Francisco Gi...",
      "price": 0.655,
      "volume": 1757033.48,
      "source": "Polymarket"
    },
    {
      "title": "Michigan State Spartans vs. Connectic...",
      "price": 0.455,
      "volume": 1730508.73,
      "source": "Polymarket"
    },
    {
      "title": "Hawks vs. Celtics",
      "price": 0.335,
      "volume": 1319530.61,
      "source": "Polymarket"
    },
    {
      "title": "Pelicans vs. Raptors",
      "price": 0.245,
      "volume": 1244793.66,
      "source": "Polymarket"
    },
    {
      "title": "Will Crude Oil (CL) hit (HIGH) $100 b...",
      "price": 0.7825,
      "volume": 1077089.51,
      "source": "Polymarket"
    },
    {
      "title": "US forces enter Iran by April 30?",
      "price": 0.585,
      "volume": 1063676.12,
      "source": "Polymarket"
    },
    {
      "title": "St. John's Red Storm vs. Duke Blue De...",
      "price": 0.275,
      "volume": 1017410.81,
      "source": "Polymarket"
    },
    {
      "title": "Athletics vs. Toronto Blue Jays",
      "price": 0.385,
      "volume": 904745.27,
      "source": "Polymarket"
    },
    {
      "title": "Kansas City Royals vs. Atlanta Braves",
      "price": 0.435,
      "volume": 895913.01,
      "source": "Polymarket"
    },
    {
      "title": "Red Wings vs. Sabres",
      "price": 0.425,
      "volume": 837586.0,
      "source": "Polymarket"
    }
  ],
  "sources": {
    "polymarket": true,
    "kalshi": false
  }
}