{
  "markets": [
    {
      "title": "Will FC Barcelona win on 2026-04-04?",
      "price": 0.485,
      "volume": 4553693.21,
      "source": "Polymarket"
    },
    {
      "title": "US forces enter Iran by April 30?",
      "price": 0.825,
      "volume": 4220102.75,
      "source": "Polymarket"
    },
    {
      "title": "Spurs vs. Nuggets",
      "price": 0.535,
      "volume": 1905911.04,
      "source": "Polymarket"
    },
    {
      "title": "Connecticut Huskies vs. Illinois Figh...",
      "price": 0.455,
      "volume": 1495721.07,
      "source": "Polymarket"
    },
    {
      "title": "Spread: Spurs (-2.5)",
      "price": 0.475,
      "volume": 1130540.9,
      "source": "Polymarket"
    },
    {
      "title": "Pistons vs. 76ers",
      "price": 0.575,
      "volume": 870154.8,
      "source": "Polymarket"
    },
    {
      "title": "Will the San Antonio Spurs win the 20...",
      "price": 0.1855,
      "volume": 844479.7,
      "source": "Polymarket"
    },
    {
      "title": "Arizona Wildcats vs. Michigan Wolverines",
      "price": 0.485,
      "volume": 839295.88,
      "source": "Polymarket"
    }
  ],
  "sources": {
    "polymarket": true,
    "kalshi": false
  }
}