{
  "markets": [
    {
      "title": "US x Iran permanent peace deal by Apr...",
      "price": 0.045,
      "volume": 1711521.82,
      "source": "Polymarket"
    },
    {
      "title": "Will Arsenal FC win on 2026-04-25?",
      "price": 0.705,
      "volume": 1489878.73,
      "source": "Polymarket"
    },
    {
      "title": "Will Bitcoin dip to $65,000 in April?",
      "price": 0.0315,
      "volume": 1160231.74,
      "source": "Polymarket"
    },
    {
      "title": "US x Iran diplomatic meeting by April...",
      "price": 0.21,
      "volume": 1026431.3,
      "source": "Polymarket"
    },
    {
      "title": "Thunder vs. Suns",
      "price": 0.775,
      "volume": 893155.59,
      "source": "Polymarket"
    }
  ],
  "sources": {
    "polymarket": true,
    "kalshi": false
  }
}